bezierview/__init__.py
bezierview/bezier.py
bezierview/view.py
bezierview-0.0.3.dist-info/LICENSE
bezierview-0.0.3.dist-info/METADATA
bezierview-0.0.3.dist-info/WHEEL
bezierview-0.0.3.dist-info/top_level.txt
bezierview-0.0.3.dist-info/RECORD
